_spellcheck.cp37-win_amd64.pyd
pywin32_cffi_spellcheck-0.1.dist-info/METADATA
pywin32_cffi_spellcheck-0.1.dist-info/WHEEL
pywin32_cffi_spellcheck-0.1.dist-info/top_level.txt
pywin32_cffi_spellcheck-0.1.dist-info/RECORD
