Metadata-Version: 2.1
Name: pywin32-cffi-spellcheck
Version: 0.1
Summary: cffi bindings for Spellcheck.h on Windows
Home-page: https://github.com/pyenchant/pywin32-cffi-spellcheck
Author: Dimitri Merejkowsky
Author-email: UNKNOWN
License: UNKNOWN
Platform: UNKNOWN
Classifier: Programming Language :: Python :: 3.5
Classifier: Programming Language :: Python :: 3.6
Classifier: Programming Language :: Python :: 3.7
Classifier: Programming Language :: Python :: 3.8
Requires-Dist: cffi (>=1.12)
